{
 "name": "المُستقرِئ",
 "title": "محلل استراتيجي · مساعد ذكاء اصطناعي",
 "text": "شكرًا لك. المشهد اليوم يُقرأ من ثلاث زوايا: الأولى هي الحزم العملياتي لترامب الذي يربط وقف الضربات بإذعان طهران لصفقة، مدعومًا بتأكيد وزير الطاقة بأن المهمة مستمرة. الثانية هي الرد الإيراني الذي تجاوز الخطوط باستهداف مواقع في الكويت والبحرين واختراق الأجواء الأردنية. الثالثة هي الخيارات المستقبلية، حيث يبرز سيناريو التصعيد الأوسع كالأرجح بنسبة 55%، مدفوعًا باحتمالية ضربات أمريكية أعمق تطال البنية التحتية والجسور رداً على أي خسائر بشرية، مع محاولات إيرانية لتهديد الملاحة، وهو ما يعيد إلى الأذهان سابقة المواجهة البحرية عام 1988 في الخليج. وتبقى هذه قراءةً احتمالية، والمؤشر الحاسم هو مدى قدرة الدفاعات الجوية على منع سقوط خسائر بشرية أمريكية جديدة.",
 "audio": "",
 "src": "2026-07-20T07:06+00:00",
 "avatar": "analyst.jpg",
 "updated": "2026-07-20T07:06+00:00"
}