{
 "checked": 43,
 "flags": [
  {
   "h": "إيران تستهدف الكويت والبحرين وأمريكا ترد على مقتل جنودها بالأردن",
   "issue": "إقحام الأردن وهو دولة غير مشاركة في الأزمة بالمخالفة للحصيلة الرسمية",
   "action": "حُذف"
  },
  {
   "h": "داخلية السعودية تعلن إعدام مصري وتكشف عن اسمه وجريمته",
   "issue": "خبر جنائي وقضائي محلي لا يرتبط بالأزمة العسكرية الجارية",
   "action": "حُذف"
  },
  {
   "h": "مسؤول سابق: انكماش اقتصاد الكويت مؤقت ومرتبط بإغلاق هرمز",
   "issue": "الخبر في القسم الخطأ حيث يخص قسم الاقتصاد لا إيران",
   "action": "خُفّض"
  },
  {
   "h": "الكويت: تعرُّض محطة ثانية لتوليد الكهرباء لهجوم إيراني",
   "issue": "الخبر في القسم الخطأ حيث يخص قسم الخليج لا إيران",
   "action": "خُفّض"
  },
  {
   "h": "الأردن يكذّب بيان سفارة أميركا بشأن إخلاء مطار وميناء العقبة",
   "issue": "إدراج الأردن كدولة مواجهة عسكرية ومشاركة بالاعتراض بالمخالفة للحصيلة",
   "action": "حُذف"
  },
  {
   "h": "عرفان إسفندياري وگل‌محمد محمدي من معتقلي احتجاجات دي يُعدمون في إيران",
   "issue": "خبر قضائي وجنائي محلي لا يرتبط مباشرة بالعمليات العسكرية الجارية",
   "action": "حُذف"
  },
  {
   "h": "قصة أول لقاء بين ميسي ولامين يامال: «معجزة من قلب القدر»",
   "issue": "خبر رياضي ومشاهير يقع تماماً خارج نطاق واهتمامات المنصة",
   "action": "حُذف"
  },
  {
   "h": "«غياب» مجتبى خامنئي.. هل تستطيع الجمهورية الإسلامية قيادة غائبة؟",
   "issue": "مادة تحليلية وتكهنات سياسية لا تغطي أحداثاً أمنية أو عسكرية آنية",
   "action": "حُذف"
  },
  {
   "h": "اعتقال مدرب استقلال التركي في مطار طهران لحمله نقوداً نقدية",
   "issue": "خبر محلي ورياضي يقع خارج اهتمامات المنصة كلياً",
   "action": "حُذف"
  },
  {
   "h": "محمد أميني دهقاني تعرض للتعذيب وأُجبر على الاعتراف قبل إعدامه",
   "issue": "موضوع حقوقي وقضائي محلي غير مرتبط بالأحداث العسكرية الجارية",
   "action": "حُذف"
  },
  {
   "h": "الجمهورية الإسلامية تعدم عرفان إسفندياري وگل‌محمد محمدي من معترضي دي",
   "issue": "خبر قضائي محلي وتكرار لخبر إعدام معتقلي الاحتجاجات",
   "action": "حُذف"
  },
  {
   "h": "عباس عراقجي: قصف البيت تم عبر ثغرة أمنية وهذه الثغرة لا تزال موجودة",
   "issue": "صياغة غير دقيقة وتكرار لنفس تصريحات عراقجي حول الثغرة الأمنية",
   "action": "حُذف"
  },
  {
   "h": "ترامب، وليس إيران، هو الخطر الأكبر على العالم – مقال في الغارديان",
   "issue": "مقال رأي وتحليل سياسي عام لا يعنى بالأحداث الأمنية الجارية",
   "action": "حُذف"
  },
  {
   "h": "هل يقود الذكاء الاصطناعي أوراكل إلى حافة التصنيف الرديء؟",
   "issue": "تقرير تقني وتجاري عام يقع خارج نطاق الأزمة الجيوسياسية للمنصة",
   "action": "حُذف"
  },
  {
   "h": "تعيد إحياء أفضل أهداف بيليه بالذكاء الاصطناعي.. لم تلتقطه الكاميرات قبل 67 عامًا",
   "issue": "خبر رياضي وتقني استهلاكي خارج دائرة اهتمام المنصة كلياً",
   "action": "حُذف"
  },
  {
   "h": "ذكاء اصطناعي.. كيمي كا3 الصيني ينافس أوبن أيه.آي وأنثروبيك",
   "issue": "مادة تقنية تجارية عامة لا تمت بصلة للأزمة الأمنية والجيوسياسية",
   "action": "حُذف"
  },
  {
   "h": "لا يُصلح الذكاء الاصطناعي ما أفسدته المؤسسة",
   "issue": "مقال رأي وفلسفة تقنية عامة خارج صلب تغطية المنصة",
   "action": "حُذف"
  },
  {
   "h": "كيمي كيه 3.. سلاح صيني جديد في سباق الذكاء الاصطناعي العالمي",
   "issue": "خبر تقني عام وتكرار لنفس موضوع النموذج الصيني خارج النطاق",
   "action": "حُذف"
  },
  {
   "h": "ليس الذكاء الاصطناعي.. مستثمر صيني يكشف نقطة ضعف بلاده في سباقها مع أميركا",
   "issue": "تقرير تجاري وتقني عام لا يعنى بالقضايا الأمنية والعسكرية للأزمة",
   "action": "حُذف"
  },
  {
   "h": "الأخير يثير الجدل .. روبوت الدردشة يتصرف من تلقاء نفسه",
   "issue": "أخبار تقنية استهلاكية خارج صلب تغطية المنصة بالإضافة لوجوده بالقسم الخطأ",
   "action": "حُذف"
  },
  {
   "h": "الولايات المتحدة تجدد ضرباتها على إيران بعد مقتل جنديين أمريكيين في هجوم إيراني على الأردن",
   "issue": "مخالفة للحصيلة الرسمية بإدراج الأردن كدولة مواجهة عسكرية وموقع للاشتباك",
   "action": "حُذف"
  }
 ],
 "verdict": "تم تدقيق كافة المواد الإخبارية البالغ عددها ٤٣ مادة واستبعاد المخالفات وتصويب توجيه الأقسام بدقة تامة.",
 "applied": {
  "removed": 19,
  "downgraded": 2
 },
 "rules_v": 15,
 "updated": "2026-07-19T12:50+00:00"
}