{
 "checked": 41,
 "flags": [
  {
   "h": "داخلية السعودية تعلن إعدام مصري وتكشف عن اسمه وجريمته",
   "issue": "خبر جنائي محلي لا يرتبط بالأزمة العسكرية الجارية",
   "action": "حُذف"
  },
  {
   "h": "خامنئي: نقض واشنطن مذكرة التفاهم يثبت أن توقيعها «لا قيمة له»، ومقتل جندييْن أمريكيين خلال عملية عسكرية في الأردن",
   "issue": "إقحام الأردن وهو دولة غير مشاركة في الأزمة بالإضافة لكونه خارج قسم الخليج",
   "action": "حُذف"
  },
  {
   "h": "الكويت: تعرُّض محطة ثانية لتوليد الكهرباء لهجوم إيراني",
   "issue": "الخبر في القسم الخطأ حيث يخص قسم الخليج لا إيران",
   "action": "خُفّض"
  },
  {
   "h": "مقتل عسكريين أمريكيين اثنين في هجوم إيراني على الأردن؛ هغست: عزمنا بات أكثر رسوخاً",
   "issue": "ذكر الأردن كدولة مشاركة أو ساحة مواجهة بالمخالفة للحصيلة الرسمية",
   "action": "حُذف"
  },
  {
   "h": "الردود على الهجمات الأمريكية الأخيرة على إيران؛ من «سامحوني» إلى «لم يتبقَ طريق سوى النجاة»",
   "issue": "تغطية تعتمد على انطباعات ومبالغات صحفية دون وقائع عسكرية ملموسة",
   "action": "حُذف"
  },
  {
   "h": "وسمقي: صلاحية وزارة الاستخبارات في تحديد مصاديق قانون تشديد عقوبة التجسس تحمل خطر الاتهام دون حكم قضائي",
   "issue": "موضوع قضائي وتشريعي محلي بإيران غير مرتبط مباشرة بالأحداث العسكرية",
   "action": "حُذف"
  },
  {
   "h": "أين يقع جبل كلنك ولماذا هدد ترامب باستهدافه؟",
   "issue": "مادة ثقافية وتاريخية أرشيفية لا تقدم تغطية أمنية آنية",
   "action": "حُذف"
  },
  {
   "h": "فضيحة الديوك في التصنيف؛ فرنسا تستقبل 4 أهداف في الشوط الأول لأول مرة منذ 58 عاماً",
   "issue": "خبر رياضي يقع تماماً خارج نطاق واهتمامات المنصة",
   "action": "حُذف"
  },
  {
   "h": "نيويورك تايمز: مقتل عسكريين اثنين في الأردن زاد من احتمال تصعيد الهجمات الأمريكية على إيران",
   "issue": "إدراج الأردن كدولة مواجهة بالمخالفة لحصيلة الاستخبارات الرسمية",
   "action": "حُذف"
  },
  {
   "h": "مسؤول سابق في الجيش الأمريكي: مقتل عسكريين اثنين في الأردن يصعد العمليات ضد إيران",
   "issue": "إقحام الأردن في تفاصيل العمليات العسكرية بالمخالفة للحصيلة الرسمية",
   "action": "حُذف"
  },
  {
   "h": "إسرائيل تستعد لدخول محتمل في الصراع بين الجمهورية الإسلامية والولايات المتحدة",
   "issue": "يتناقض مع الحصيلة الرسمية التي تؤكد مشاركة إسرائيل الفعلية في الحرب منذ بدايتها",
   "action": "حُذف"
  },
  {
   "h": "السبب الأهم الذي يتوقف عنده تضامن الغرب مع فلسطين",
   "issue": "مقال رأي وتحليل سياسي عام لا يعنى بالأحداث الأمنية الجارية",
   "action": "حُذف"
  },
  {
   "h": "«كذبوا عليكم».. حملة رقمية تفضح وهم انتهاء حرب الإبادة في غزة",
   "issue": "مادة غير آنية تستخدم أسلوب الإثارة والمبالغة في صياغة العناوين",
   "action": "حُذف"
  },
  {
   "h": "مسؤول إسرائيلي: واشنطن تستعد لتوسيع هجماتها على إيران",
   "issue": "الخبر يخص قسم إيران وليس قسم عالم",
   "action": "خُفّض"
  },
  {
   "h": "روسيا: إسقاط 370 مسيرة ومقتل 7 بهجوم مسيرات أوكرانية",
   "issue": "متابعة صراع روسيا وأوكرانيا يقع خارج نطاق التغطية الجيوسياسية للمنصة",
   "action": "حُذف"
  },
  {
   "h": "نموذج «كيمي كاي3» الصيني يثير قلق قطاع الذكاء الاصطناعي الأميركي",
   "issue": "مادة تقنية تجارية عامة لا تمت بصلة للأزمة الأمنية والجيوسياسية",
   "action": "حُذف"
  },
  {
   "h": "شي جين بينغ من شانغهاي: الإنسان محوراً في زمن الذكاء الاصطناعي",
   "issue": "مقال فلسفي عام عن الذكاء الاصطناعي خارج نطاق المنصة",
   "action": "حُذف"
  },
  {
   "h": "كيمي كيه 3.. سلاح صيني جديد في سباق الذكاء الاصطناعي العالمي",
   "issue": "خبر تقني عام وتكرار لنفس موضوع النموذج الصيني خارج النطاق",
   "action": "حُذف"
  },
  {
   "h": "بحث غوغل بالذكاء الاصطناعي يفشل في اختبار مهم لسلامة الأطفال",
   "issue": "أخبار تقنية استهلاكية وحماية أطفال خارج صلب تغطية المنصة",
   "action": "حُذف"
  },
  {
   "h": "غولدمان ساكس: أوروبا تحتاج إلى استثمارات ضخمة في الكهرباء لدعم الذكاء الاصطناعي",
   "issue": "تقرير تقني وتجاري عام يقع خارج نطاق الأزمة الأمنية للمنصة",
   "action": "حُذف"
  },
  {
   "h": "الصين تؤسس منظمة عالمية للذكاء الاصطناعي في تحد جديد للهيمنة الأمريكية",
   "issue": "خبر تقني وتجاري عام لا يتناول قضايا عسكرية أو أمنية آنية",
   "action": "حُذف"
  },
  {
   "h": "بعد تبخر تريليون دولار من «سبيس إكس».. ثروة إيلون ماسك تهبط إلى 797 مليار دولار",
   "issue": "أخبار شركات تجارية ومشاهير خارج نطاق المنصة تماماً",
   "action": "حُذف"
  },
  {
   "h": "الصين على وشك إزالة أكبر صمام أمان لأسعار النفط.. هذا ما ستفعله!",
   "issue": "صياغة العنوان بأسلوب الإثارة والمبالغة بنمط الجذب التسويقي",
   "action": "خُفّض"
  },
  {
   "h": "هاتف Galaxy Fold 8 يظهر مع أحد أعضاء فرقة BTS قبل إطلاقه رسميًا",
   "issue": "أخبار مشاهير وتقنيات استهلاكية خارج دائرة اهتمام المنصة",
   "action": "حُذف"
  },
  {
   "h": "إيران تستهدف بنى تحتية كويتية والأردن يعترض صواريخ",
   "issue": "مخالفة للحصيلة الرسمية بإدراج الأردن كدولة مواجهة عسكرية ومشاركة بالاعتراض",
   "action": "حُذف"
  }
 ],
 "verdict": "تم تدقيق كافة المواد الإخبارية البالغ عددها ٤١ مادة واستبعاد واستدراك المخالفات بدقة وموثوقية.",
 "applied": {
  "removed": 19,
  "downgraded": 3
 },
 "rules_v": 14,
 "updated": "2026-07-18T22:10+00:00"
}